[{"pivotRow":"2012","B":"0","C":"0","International Gold":"1","National Gold":"1","National Platinum":"0","National Silver":"0","State Bronze":"0","State Gold":"1","State Silver":"0","Total":"3"},{"pivotRow":"2013","B":"0","C":"1","International Gold":"0","National Gold":"7","National Platinum":"0","National Silver":"6","State Bronze":"7","State Gold":"6","State Silver":"12","Total":"39"},{"pivotRow":"2014","B":"0","C":"0","International Gold":"0","National Gold":"5","National Platinum":"1","National Silver":"6","State Bronze":"6","State Gold":"6","State Silver":"11","Total":"35"},{"pivotRow":"2015","B":"13","C":"6","International Gold":"0","National Gold":"0","National Platinum":"0","National Silver":"1","State Bronze":"4","State Gold":"4","State Silver":"14","Total":"42"},{"pivotRow":"2016","B":"9","C":"31","International Gold":"0","National Gold":"0","National Platinum":"0","National Silver":"0","State Bronze":"5","State Gold":"0","State Silver":"8","Total":"53"},{"pivotRow":"Total","B":"22","C":"38","International Gold":"1","National Gold":"13","National Platinum":"1","National Silver":"7","State Bronze":"22","State Gold":"11","State Silver":"45","Total":"172"}]